{"cameraMode":{"drawMode":0,"name":"Shaded","section":"Shading Mode"},"sceneLighting":true,"audioPlay":false,"sceneViewState":{"m_AlwaysRefresh":false,"showFog":true,"showSkybox":true,"showFlares":true,"showImageEffects":true,"showParticleSystems":true,"showVisualEffectGraphs":true,"m_FxEnabled":true},"in2DMode":false,"pivot":{"x":-10.585869789123536,"y":2.9520134925842287,"z":2.273383140563965},"rotation":{"x":-0.16398899257183076,"y":0.4543476700782776,"z":-0.08549118787050247,"w":-0.8714552521705627},"size":4.691214084625244,"orthographic":false}