{"cameraMode":{"drawMode":0,"name":"Shaded","section":"Shading Mode"},"sceneLighting":true,"audioPlay":false,"sceneViewState":{"m_AlwaysRefresh":false,"showFog":true,"showSkybox":true,"showFlares":true,"showImageEffects":true,"showParticleSystems":true,"showVisualEffectGraphs":true,"m_FxEnabled":true},"in2DMode":false,"pivot":{"x":-7.289350509643555,"y":0.23185992240905763,"z":2.9134037494659426},"rotation":{"x":0.08408661931753159,"y":-0.679286003112793,"z":0.07880981266498566,"w":0.7247918248176575},"size":6.470339775085449,"orthographic":false}